verchew/__init__.py
verchew/__main__.py
verchew/script.py
verchew/tests/__init__.py
verchew/tests/conftest.py
verchew/tests/test_script.py
verchew/wrapper.sh
verchew-3.4.2.dist-info/LICENSE.md
verchew-3.4.2.dist-info/METADATA
verchew-3.4.2.dist-info/WHEEL
verchew-3.4.2.dist-info/entry_points.txt
verchew-3.4.2.dist-info/RECORD
