Metadata-Version: 2.1
Name: verchew
Version: 3.4.2
Summary: System dependency version checker.
Home-page: https://pypi.org/project/verchew
License: MIT
Keywords: dependencies,configuration management,continuous integration
Author: Jace Browning
Author-email: jacebrowning@gmail.com
Requires-Python: >=3.8,<4.0
Classifier: Development Status :: 5 - Production/Stable
Classifier: Environment :: Console
Classifier: Intended Audience :: Developers
Classifier: License :: OSI Approved :: MIT License
Classifier: Natural Language :: English
Classifier: Operating System :: OS Independent
Classifier: Programming Language :: Python :: 3
Classifier: Programming Language :: Python :: 3.8
Classifier: Programming Language :: Python :: 3.9
Classifier: Programming Language :: Python :: 3.10
Classifier: Programming Language :: Python :: 3.11
Classifier: Programming Language :: Python :: 2.7
Classifier: Topic :: Software Development
Classifier: Topic :: Software Development :: Build Tools
Classifier: Topic :: Software Development :: Testing
Classifier: Topic :: System :: Installation/Setup
Classifier: Topic :: Utilities
Project-URL: Documentation, https://verchew.readthedocs.io
Project-URL: Repository, https://github.com/jacebrowning/verchew
